gtaz/__init__.py
gtaz/gamepads.py
gtaz/keyboard_actions.py
gtaz/screens.py
gtaz/segments.py
gtaz/windows.py
gtaz/agency_move/inference.py
gtaz/agency_move/realtime.py
gtaz/agency_move/recognizes.py
gtaz/agency_move/recognizes_v2.py
gtaz/agency_move/train.py
gtaz/characters/interacts.py
gtaz/menus/commons.py
gtaz/menus/interacts.py
gtaz/menus/locates.py
gtaz/menus/navigates.py
gtaz/menus/ocrs.py
gtaz/nets/tracks.py
gtaz/workers/mode_switch.py
gtaz-0.7.dist-info/licenses/LICENSE
gtaz-0.7.dist-info/METADATA
gtaz-0.7.dist-info/WHEEL
gtaz-0.7.dist-info/top_level.txt
gtaz-0.7.dist-info/RECORD
