Metadata-Version: 2.4
Name: gtaz
Version: 0.7
Summary: Visual-based AI for real-time tasks in GTAV
Author: Hansimov
Project-URL: Homepage, https://github.com/Hansimov/gtaz
Project-URL: Issues, https://github.com/Hansimov/gtaz/issues
Classifier: Programming Language :: Python :: 3
Classifier: License :: OSI Approved :: MIT License
Classifier: Operating System :: OS Independent
Requires-Python: >=3.8
License-File: LICENSE
Requires-Dist: tclogger
Requires-Dist: vgamepad
Requires-Dist: numpy
Requires-Dist: Pillow
Provides-Extra: dev
Requires-Dist: tclogger; extra == "dev"
Requires-Dist: vgamepad; extra == "dev"
Requires-Dist: numpy; extra == "dev"
Requires-Dist: Pillow; extra == "dev"
Requires-Dist: torch; extra == "dev"
Requires-Dist: torchvision; extra == "dev"
Requires-Dist: timm; extra == "dev"
Provides-Extra: gpu
Provides-Extra: cpu
Dynamic: license-file
